[{"id":"IXMPBsjL","user_id":"22f7f961-1151-4660-85f4-ad5d9f042958","name":"new level","description":"auto desc","published":true,"data":{"rooms": [{"scale": 2.25, "stage": {"locked": false, "matrix": ["", ["", "", "", "", "", "", "", "", "", "", "", "", "", "", "", "", "", "", "", "", "", "", "", "", "", "", "", "", "", "", "", "", "", "", "", "", "", "", "", "", "", "", "", "", "", "", "", "", "", "", "", "", "", "", "", "", "", "", "", "", "", "", "", "", "", "", "", "", "", "", "", "", "", "", "In", "In", "In", "In"], ["", "", "", "", "", "", "", "", "", "", "", "", "", "", "", "", "", "", "", "", "", "", "", "", "", "", "", "", "", "", "", "", "", "", "$", "", "$", "", "", "", "", "", "", "", "", "", "", "", "", "", "", "", "", "", "", "", "", "", "", "", "", "", "", "", "", "", "", "In", "", "In", "In", "In", "In", "", "In", "", "", "In"], ["", "", "", "", "", "", "", "", "", "", "", "", "", "", "", "", "", "", "", "", "", "", "", "", "", "", "", "", "", "", "Brn", "", "", "", "", "", "", "", "", "", "", "", "", "", "", "", "", "", "", "", "", "", "", "", "", "", "", "", "", "", "", "", "", "", "", "", "", "In", "", "", "", "", "In", "", "In", "", "", "In"], ["", "", "", "", "", "", "", "", "", "", "", "", "", "", "", "", "", "", "", "", "", "", "", "", "", "", "", "", "", "", "", "Bltr", "Bltr", "Bltr", "?", "?", "?", "", "", "", "", "", "", "", "", "", "", "", "", "", "", "", "", "", "", "", "", "", "", "", "", "", "", "", "", "", "", "In", "", "", "", "", "In", "", "In", "", "In", "In"], ["", "", "", "", "", "", "", "", "", "", "", "", "", "", "", "", "", "", "", "", "", "", "", "", "", "", "", "", "", "", "", "", "", "", "", "", "", "", "", "", "", "", "", "", "", "", "", "", "", "", "", "", "", "", "", "", "In", "?", "?", "?", "", "", "", "", "", "", "", "In", "In", "In", "In", "", "In", "", "", "", "In", "In"], ["", "", "", "", "", "", "", "", "", "", "", "", "", "", "", "", "", "", "", "", "", "", "", "", "", "", "", "?", "$", "?", "", "", "", "", "", "", "", "", "", "", "", "?", "", "", "", "", "", "", "In", "In", "", "", "", "", "", "", "In", "", "", "", "", "", "", "", "", "", "", "In", "", "", "", "", "In", "", "", "", "In", "In"], ["", "", "", "", "", "", "", "", "", "", "", "", "", "", "", "", "", "", "", "", "", "", "", "", "", "", "", "", "", "", "", "", "", "", "", "", "", "", "", "", "", "?", "", "", "", "", "", "", "", "In", "", "", "", "", "", "", "In", "", "", "", "", "", "", "", "", "", "", "In", "", "", "", "", "In", "", "", "In", "In", "In"], ["", "", "", "", "", "", "", "", "", "", "", "", "", "", "", "", "", "", "", "", "", "", "", "", "", "", "", "", "", "", "", "", "", "", "", "", "", "", "", "", "", "?", "In", "In", "In", "", "", "", "", "In", "", "", "", "", "", "", "In", "In", "In", "In", "", "", "", "", "", "", "", "In", "", "In", "In", "", "In", "", "In", "In", "In", "In"], ["", "", "", "", "", "", "", "", "", "", "", "", "", "", "", "", "", "", "", "", "", "", "", "", "", "", "", "", "$", "", "", "", "", "", "", "", "", "", "", "", "", "", "", "", "", "", "", "", "?", "?", "", "", "", "", "", "", "", "", "", "", "", "", "", "", "", "", "", "In", "", "", "In", "", "In", "", "In", "In", "In", "In"], ["", "", "", "", "", "", "", "", "", "", "", "", "", "", "", "", "", "", "", "", "", "", "", "", "", "", "", "", "$", "", "Brn", "", "", "", "$", "$", "", "$", "$", "", "$", "$", "", "", "", "", "", "", "", "", "", "", "", "", "", "", "", "", "", "", "", "", "", "", "", "", "", "In", "", "", "In", "In", "In", "In", "In", "In", "In", "In"], ["", "", "", "", "", "", "", "", "", "", "", "", "", "", "", "", "", "", "", "", "", "", "", "", "", "", "", "", "", "", "", "Bltr", "Bltr", "Bltr", "", "", "", "", "", "", "", "", "", "", "", "", "", "", "", "", "", "", "", "Brn", "Brn", "", "", "", "", "", "", "", "", "", "", "", "", "In", "", "", "In", "In", "In", "In", "In", "In", "In", "In"], ["", "", "", "", "", "", "", "", "", "", "", "", "", "", "", "", "", "", "", "", "", "", "", "", "", "", "", "", "", "", "", "", "", "", "", "", "?", "", "", "?", "", "", "", "", "", "?", "In", "In", "In", "?", "", "", "In", "In", "In", "In", "In", "In", "In", "In", "In", "In", "In", "In", "In", "In", "In", "In", "In", "In", "In", "In", "In", "In", "In", "In", "In", "In"], ["", "", "", "", "", "", "", "", "", "", "", "", "", "", "", "", "", "", "", "", "", "", "", "", "", "", "", "", "", "", "", "", "", "", "", "", "", "", "", "", "", "", "", "", "", "", "", "", "", "", "", "", "", "", "", "", "", "", "", "In", "In", "In", "In", "In", "In", "In", "In", "In", "In", "In"], ["", "", "", "", "", "", "", "", "", "", "", "", "", "", "", "", "", "", "", "", "", "$", "$", "", "", "", "", "", "", "", "", "", "", "", "", "", "", "", "", "", "", "", "", "", "", "", "", "", "", "", "", "", "", "", "", "", "?", "?", "?", "In", "In", "In", "In", "In", "In", "In", "In"], ["?", "", "", "", "", "", "", "", "", "", "", "", "", "", "", "", "", "", "", "$", "$", "", "", "", "", "", "", "", "", "", "", "", "", "?", "", "", "", "", "", "", "", "", "?", "", "", "", "", "", "", "", "", "", "", "", "", "", "", "", "", "In", "In", "In", "In"], ["", "", "", "", "", "", "", "", "", "", "", "", "", "", "", "", "", "", "", "", "", "", "", "Bl", "Bl", "Bl", "Bl", "Bl", "Bl", "", "", "", "", "", "", "", "", "", "", "", "", "", "?", "", "", "", "", "Brn", "", "In", "In", "In", "In", "In", "In", "In", "In", "In", "In", "In"], ["", "", "", "", "", "", "", "", "", "", "", "", "", "", "", "", "", "", "", "", "", "", "", "", "", "", "", "", "", "", "", "", "", "", "", "", "", "", "", "", "", "", "", "In", "In", "In", "In", "In", "In", "In", "In", "In"], ["?", "?", "", "", "", "", "", "", "", "", "", "", "", "", "", "", "", "", "", "", "", "", "", "", "", "", "", "", "", "", "", "", "?", "?"], "", ["", "", "", "", "", "", "", "", "", "", "", "", "", "", "", "", "", "", "", "", "", "", "", "", "", "", "", "", "", "", "", "", "$", "$", "", "", "", "", "Brn"], "", ["", "", "", "", "", "", "", "", "", "", "", "", "", "", "", "Brn"], ["", "", "", "", "", "", "", "", "", "", "", "", "", "Brn"], ["", "", ""], "", ""], "entities": [{"x": 0, "y": 400, "id": 11, "type": "WoodColumnWide", "settings": {"width": 2, "height": 2}}, {"x": 32, "y": 400, "id": 12, "type": "WoodColumnWide", "settings": {"width": 2, "height": 2}}, {"x": 64, "y": 400, "id": 13, "type": "WoodColumnWide", "settings": {"width": 2, "height": 2}}, {"x": 96, "y": 400, "id": 14, "type": "WoodColumnWide", "settings": {"width": 2, "height": 2}}, {"x": 128, "y": 400, "id": 15, "type": "WoodColumnWide", "settings": {"width": 2, "height": 2}}, {"x": 160, "y": 400, "id": 16, "type": "WoodColumnWide", "settings": {"width": 2, "height": 2}}, {"x": 160, "y": 384, "id": 17, "type": "AirshipPlatform", "settings": {"cap": "flat-flat", "width": 6, "resizing": false}}, {"x": 224, "y": 368, "id": 18, "type": "AirshipPlatform", "settings": {"cap": "flat-flat", "width": 3}}, {"x": 272, "y": 368, "id": 19, "type": "AirshipPlatform", "settings": {"cap": "flat-flat", "width": 4, "resizing": false}}, {"x": 256, "y": 352, "id": 20, "type": "AirshipPlatform", "settings": {"cap": "flat-flat", "width": 3}}, {"x": 304, "y": 352, "id": 21, "type": "AirshipPlatform", "settings": {"cap": "flat-flat", "width": 4, "resizing": false}}, {"x": 336, "y": 368, "id": 22, "type": "AirshipPlatform", "settings": {"cap": "flat-flat", "width": 2, "resizing": false}}, {"x": 320, "y": 384, "id": 23, "type": "AirshipPlatform", "settings": {"cap": "flat-flat", "width": 3}}, {"x": 256, "y": 384, "id": 24, "type": "AirshipPlatform", "settings": {"cap": "flat-flat", "width": 4, "resizing": false}}, {"x": 192, "y": 400, "id": 25, "type": "AirshipPlatform", "settings": {"cap": "flat-flat", "width": 11, "resizing": false}}, {"x": 336, "y": 336, "id": 26, "type": "AirshipPlatform", "settings": {"cap": "flat-flat", "width": 2, "resizing": false}}, {"x": 288, "y": 336, "id": 27, "type": "AirshipPlatform", "settings": {"cap": "flat-flat", "width": 3}}, {"x": 192, "y": 416, "id": 28, "type": "AirshipPlatform", "settings": {"cap": "flat-flat", "width": 11, "resizing": false}}, {"x": 176, "y": 352, "id": 35, "type": "BillBlaster", "settings": {"height": 2, "orientation": "up"}}, {"x": 112, "y": 384, "id": 36, "type": "BillBlasterNoBody"}, {"x": 336, "y": 256, "id": 44, "type": "AirshipCrate", "settings": {"width": 2, "height": 5}}, {"x": 304, "y": 272, "id": 45, "type": "AirshipCrate", "settings": {"width": 2, "height": 4}}, {"x": 0, "y": 336, "id": 50, "type": "AirshipPlatform", "settings": {"cap": "flat-flat", "width": 3}}, {"x": 112, "y": 288, "id": 51, "type": "WoodColumnWide", "settings": {"width": 2, "height": 2}}, {"x": 128, "y": 256, "id": 52, "type": "BillBlaster", "settings": {"height": 2, "orientation": "up"}}, {"x": 112, "y": 272, "id": 53, "type": "BillBlasterNoBody"}, {"x": 464, "y": 256, "id": 74, "type": "AirshipCrate", "settings": {"width": 2, "height": 5}}, {"x": 464, "y": 336, "id": 75, "type": "WoodColumnWide", "settings": {"width": 14, "height": 6, "resizing": false}}, {"x": 672, "y": 272, "id": 76, "type": "BillBlaster", "settings": {"height": 4, "resizing": false, "orientation": "up"}}, {"x": 640, "y": 304, "id": 77, "type": "BillBlaster", "settings": {"height": 2, "orientation": "up"}}, {"x": 576, "y": 304, "id": 78, "type": "BillBlaster", "settings": {"height": 2, "orientation": "up"}}, {"x": 656, "y": 320, "id": 81, "type": "BillBlasterNoBody"}, {"x": 544, "y": 176, "id": 87, "type": "AirshipCrate", "settings": {"width": 2, "height": 4}}, {"x": 592, "y": 176, "id": 88, "type": "AirshipCrate", "settings": {"width": 2, "height": 4}}, {"x": 640, "y": 176, "id": 89, "type": "AirshipCrate", "settings": {"width": 2, "height": 4}}, {"x": 544, "y": 240, "id": 90, "type": "AirshipPlatform", "settings": {"cap": "flat-flat", "width": 8, "resizing": false}}, {"x": 464, "y": 176, "id": 105, "type": "AirshipCrate", "settings": {"width": 2, "height": 5}}, {"x": 464, "y": 144, "id": 106, "type": "BillBlaster", "settings": {"height": 2, "orientation": "up"}}, {"x": 480, "y": 64, "id": 108, "type": "WoodColumn", "settings": {"width": 1}}, {"x": 416, "y": 176, "id": 110, "type": "AirshipPlatform", "settings": {"cap": "flat-flat", "width": 3}}, {"x": 416, "y": 144, "id": 111, "type": "WoodColumnWide", "settings": {"width": 2, "height": 2}}, {"x": 416, "y": 96, "id": 113, "type": "WoodColumn", "settings": {"width": 1}}, {"x": 416, "y": 64, "id": 114, "type": "BillBlaster", "settings": {"height": 2, "orientation": "up"}}, {"x": 544, "y": 112, "id": 124, "type": "AirshipPlatform", "settings": {"cap": "flat-flat", "width": 3}}, {"x": 560, "y": 32, "id": 125, "type": "BillBlaster", "settings": {"height": 2, "orientation": "up"}}, {"x": 416, "y": 384, "id": 147, "type": "AirshipMetalPanel", "settings": {"width": 3, "height": 3}}, {"x": 368, "y": 352, "id": 148, "type": "AirshipMetalPanel", "settings": {"width": 3, "height": 3}}, {"x": 784, "y": 240, "id": 264, "type": "BillBlasterNoBody"}, {"x": 800, "y": 192, "id": 268, "type": "AirshipCrate", "settings": {"width": 2, "height": 4}}, {"x": 896, "y": 48, "id": 819, "type": "BillBlaster", "settings": {"height": 2, "orientation": "up"}}, {"x": 928, "y": 64, "id": 820, "type": "BillBlasterNoBody"}], "matrixSettings": [{"s": {"payload": "FireFlower"}, "x": 56, "y": 14}, {"s": {"payload": "StarMan"}, "x": 57, "y": 14}, {"s": {"payload": "CapeFeather"}, "x": 58, "y": 14}, {"s": {"payload": "Shoe"}, "x": 0, "y": 18}, {"s": {"payload": "Leaf"}, "x": 1, "y": 18}]}, "actors": {"locked": false, "matrix": [], "entities": [{"x": 32, "y": 368, "id": 1, "type": "Player"}, {"x": 80, "y": 384, "id": 41, "type": "RockyWrench"}, {"x": 272, "y": 336, "id": 42, "type": "RockyWrench"}, {"x": 544, "y": 320, "id": 79, "type": "RockyWrench"}, {"x": 432, "y": 128, "id": 112, "type": "RockyWrench"}, {"x": 416, "y": 368, "id": 150, "type": "RockyWrench"}, {"x": 432, "y": 368, "id": 151, "type": "RockyWrench"}, {"x": 448, "y": 368, "id": 152, "type": "RockyWrench"}, {"x": 400, "y": 336, "id": 153, "type": "RockyWrench"}, {"x": 384, "y": 336, "id": 154, "type": "RockyWrench"}, {"x": 368, "y": 336, "id": 155, "type": "RockyWrench"}, {"x": 688, "y": 112, "id": 167, "type": "RockyWrench"}, {"x": 704, "y": 256, "id": 265, "type": "RockyWrench"}, {"x": 752, "y": 176, "id": 266, "type": "RockyWrench"}, {"x": 768, "y": 80, "id": 267, "type": "RockyWrench"}, {"x": 960, "y": 176, "id": 767, "type": "SpringBoard"}, {"x": 976, "y": 176, "id": 768, "type": "SpringBoard"}, {"x": 992, "y": 176, "id": 769, "type": "SpringBoard"}, {"x": 1104, "y": 160, "id": 926, "type": "CardSlotMachine"}], "matrixSettings": []}, "settings": {"music": 0, "bgColor": 132, "bgGraphic": 5, "bgExtraColorAndEffect": 0}, "scrollOffset": {"x": 726.6666666666674, "y": -59.11111111111123}, "roomTileWidth": 96, "paletteEntries": ["CardSlotMachine", "SpringBoard", "IndestructibleBrick", "QuestionBlock", "BillBlasterNoBody", "Burner", "RockyWrench", "BillBlaster", "WoodColumnWide", "WoodColumn", "BoltUp", "BoltRight", "BoltLeft", "AirshipPlatform", "BoltDown", "AirshipMetalPanel", "AirshipCrate", "Coin", "WoodBlock"], "roomTileHeight": 27, "canDecreaseScale": true, "canIncreaseScale": true, "currentPaletteEntry": "QuestionBlock"}], "settings": {"timer": 900}},"parent_id":"IXMPBsjL","save_version":1,"created_at":"2023-09-23T22:47:18.173253","updated_at":"2023-09-23T22:47:18.173253","version":"5.2.0","user":{"username":"camilo"}}, 
 {"id":"7vRN46Ap","user_id":"22f7f961-1151-4660-85f4-ad5d9f042958","name":"new level","description":"auto desc","published":true,"data":{"rooms": [{"scale": 1.5, "stage": {"locked": false, "matrix": ["", "", "", "", "", "", "", "", "", "", "", ["", "", "", "", "", "", "", "", "", "", "", "", "", "", "", "", "", "", "", "", "", "", "", "", "", "", "", "", "", "", "", "", "Wo", "Wo", "Wo", "Wo", "Wo"], ["", "", "", "", "", "", "", "", "", "", "", "", "", "", "", "", "", "", "", "", "", "", "", "", "", "", "", "", "", "", "", "", "Wo", "", "", "", "Wo"], ["", "", "", "", "", "", "", "", "", "", "", "", "", "", "", "", "", "", "", "", "", "", "", "", "", "", "", "", "", "", "", "", "Wo", "", "", "", "Wo", "", "", "", "", "", "", "", "", "", "", "", "", "", "", "", "", "", "", "", "", "", "", "", "", "", "", "Br", "Br", "Br", "", "Br"], ["", "", "", "", "", "", "", "", "", "", "", "", "", "", "", "", "", "", "", "", "", "", "", "", "", "", "", "", "", "", "", "", "Wo", "", "", "", "Wo", "", "", "", "", "", "", "", "", "", "", "", "", "", "", "", "", "", "", "", "", "", "", "", "", "", "", "Br", "", "Br", "", ""], ["", "", "", "", "", "", "", "", "", "", "", "", "", "", "", "", "", "", "", "", "", "", "", "", "", "", "", "", "", "", "", "", "Wo", "", "Wo", "", "Wo", "", "", "", "", "", "", "", "", "", "", "", "", "", "", "", "", "", "", "", "", "", "", "", "", "", "", "Br", "Br", "Br", "", "Br"], ["", "", "", "", "", "", "", "", "", "", "", "", "", "", "", "", "", "", "", "", "", "", "", "", "", "", "", "", "", "Wo", "Wo", "Wo", "Wo", "", "Wo", "", "Wo", "", "", "", "", "", "", "", "", "", "", "", "", "", "", "", "", "", "", "", "", "", "", "", "", "", "", "Br", "", "", "", "Br"], ["", "", "", "", "", "", "", "", "", "", "", "", "", "", "", "", "", "", "", "", "", "", "", "", "", "", "", "", "", "Wo", "", "", "", "", "Wo", "", "Wo"], ["", "", "", "", "", "", "", "", "", "", "", "", "", "", "", "", "", "", "", "", "", "", "", "", "", "", "", "Wo", "Wo", "Wo", "", "", "", "", "Wo", "Hbw", "Wo", "Wo", "", "", "", "", "", "", "", "", "", "", "", "", "", "", "", "", "", "", "", "", "", "", "", "", "Br", "Br", "Br", "", "Br", "Br", "Br"], ["", "", "Br", "Br", "Br", "Br", "Br", "Br", "Br", "Br", "", "", "", "", "", "", "", "", "", "", "", "", "", "", "", "", "", "Wo", "", "", "", "Wo", "Wo", "", "Wo", "", "", "Wo", "Wo", "Wo", "Wo", "Wo", "Wo", "", "", "", "", "", "", "", "", "", "", "", "", "", "", "", "", "", "", "", "", "Br", "", "", "Br", "", "Br"], ["", "", "", "", "", "", "", "", "", "", "", "", "", "", "", "", "", "", "", "", "", "", "", "", "", "", "", "Wo", "", "", "", "Wo", "Wo", "Wo", "Wo", "", "", "", "", "", "", "", "Wo", "", "", "", "", "", "", "", "", "", "", "", "", "", "", "", "", "", "", "", "", "Br", "", "", "Br", "Br", "Br"], ["", "", "", "", "", "", "", "", "", "", "", "", "", "", "", "", "", "", "", "", "", "", "", "", "", "", "", "Wo", "", "", "", "Wo", "", "", "Wo", "", "", "", "", "", "", "", "Wo", "", "", "", "", "", "", "", "", "", "", "", "", "", "", "", "", "", "", "", "", "Br"], ["Br", "Br", "Br", "Br", "Br", "Br", "Br", "Br", "Br", "", "Wo", "", "", "", "", "", "", "", "", "", "", "", "", "", "", "", "", "Wo", "", "Wo", "", "Wo", "", "", "Wo", "", "Wo", "Wo", "Wo", "Wo", "", "", "Wo", "Wo"], ["Br", "", "", "", "", "", "", "", "Br", "", "Wo", "", "", "", "", "", "", "", "", "?", "", "", "", "", "", "", "", "", "", "Wo", "", "Wo", "", "", "Wo", "", "Wo", "Wo", "Wo", "Wo", "", "", "", "Wo"], ["Br", "", "", "", "", "", "", "", "", "", "Wo", "", "", "", "", "", "", "", "", "", "", "", "", "", "", "", "", "", "", "Wo", "", "Wo", "", "", "Wo", "", "Wo", "Wo", "Wo", "Wo", "", "", "", ""], ["Br", "", "", "", "", "", "", "", "", "", "Wo", "", "", "", "", "", "", "", "", "", "", "", "", "", "Wo", "Wo", "", "Wo", "", "Wo", "", "Wo", "", "", "Wo", "", "Wo", "Wo", "Wo", "Wo", "", "", "", ""], ""], "entities": [{"x": 0, "y": 416, "id": 11, "type": "WoodFloor", "settings": {"width": 29, "height": 1}}, {"x": 208, "y": 144, "id": 72, "type": "PipeVertical", "settings": {"height": 17, "resizing": false, "direction": "up"}}, {"x": 160, "y": 320, "id": 73, "type": "BillBlaster", "settings": {"height": 2, "orientation": "up"}}, {"x": 160, "y": 288, "id": 76, "type": "BillBlaster", "settings": {"height": 2, "orientation": "up"}}, {"x": 96, "y": 272, "id": 89, "type": "BillBlaster", "settings": {"height": 2, "orientation": "up"}}, {"x": 112, "y": 272, "id": 90, "type": "BillBlaster", "settings": {"height": 2, "orientation": "up"}}, {"x": 128, "y": 272, "id": 91, "type": "BillBlaster", "settings": {"height": 2, "orientation": "up"}}, {"x": 144, "y": 272, "id": 92, "type": "BillBlaster", "settings": {"height": 2, "orientation": "up"}}, {"x": 80, "y": 272, "id": 108, "type": "BillBlaster", "settings": {"height": 2, "orientation": "up"}}, {"x": 64, "y": 272, "id": 109, "type": "BillBlaster", "settings": {"height": 2, "orientation": "up"}}, {"x": 48, "y": 272, "id": 110, "type": "BillBlaster", "settings": {"height": 2, "orientation": "up"}}, {"x": 32, "y": 272, "id": 111, "type": "BillBlaster", "settings": {"height": 2, "orientation": "up"}}, {"x": 464, "y": 416, "id": 138, "type": "WoodFloor", "settings": {"width": 68, "height": 1}}, {"x": 1168, "y": 240, "id": 441, "type": "PipeVertical", "settings": {"height": 11, "resizing": false, "direction": "up"}}, {"x": 1200, "y": 240, "id": 442, "type": "PipeVertical", "settings": {"height": 11, "resizing": false, "direction": "up"}}, {"x": 1232, "y": 240, "id": 443, "type": "PipeVertical", "settings": {"height": 11, "resizing": false, "direction": "up"}}, {"x": 1088, "y": 336, "id": 444, "type": "ColorfulMetalBox", "settings": {"color": "orange", "width": 5, "height": 5}}, {"x": 1264, "y": 336, "id": 445, "type": "ColorfulMetalBox", "settings": {"color": "white", "width": 5, "height": 5}}], "matrixSettings": [{"s": {"payload": "Leaf"}, "x": 6, "y": 22}, {"s": {"payload": "Leaf"}, "x": 19, "y": 23}]}, "actors": {"locked": false, "matrix": [], "entities": [{"x": 32, "y": 368, "id": 1, "type": "Player"}, {"x": 112, "y": 400, "id": 67, "type": "GreenKoopaTroopa"}, {"x": 128, "y": 400, "id": 68, "type": "GreenKoopaTroopa"}, {"x": 144, "y": 400, "id": 69, "type": "GreenKoopaTroopa"}, {"x": 96, "y": 400, "id": 70, "type": "GreenKoopaTroopa"}, {"x": 80, "y": 400, "id": 71, "type": "Goomba"}, {"x": 192, "y": 400, "id": 112, "type": "SpikeTop"}, {"x": 176, "y": 400, "id": 113, "type": "SpikeTop"}, {"x": 176, "y": 384, "id": 114, "type": "SpikeTop"}, {"x": 192, "y": 384, "id": 115, "type": "SpikeTop"}, {"x": 480, "y": 400, "id": 173, "type": "SpringBoard"}, {"x": 528, "y": 304, "id": 229, "type": "SpringBoard"}, {"x": 448, "y": 400, "id": 232, "type": "SpringBoard"}, {"x": 560, "y": 400, "id": 429, "type": "SpringBoard"}, {"x": 656, "y": 384, "id": 432, "type": "CardSlotMachine"}], "matrixSettings": []}, "settings": {"music": 0, "bgColor": 132, "bgGraphic": 5, "bgExtraColorAndEffect": 0}, "scrollOffset": {"x": 208.88888888888906, "y": 37.11111111111108}, "roomTileWidth": 96, "paletteEntries": ["PlayerGhost", "ColorfulMetalBox", "HiddenBlockWithoutNote", "SpringBoard", "SpikeTop", "BillBlaster", "WoodFloor", "Brick", "Coin", "WoodBlock", "Goomba", "QuestionBlock", "GreenKoopaTroopa", "PipeVertical", "CardSlotMachine", "PSwitch"], "roomTileHeight": 27, "canDecreaseScale": true, "canIncreaseScale": true, "currentPaletteEntry": "Brick"}], "settings": {"timer": 900}},"parent_id":"7vRN46Ap","save_version":1,"created_at":"2023-09-11T22:33:38.909168","updated_at":"2023-09-11T22:33:38.909168","version":"5.2.0","user":{"username":"camilo"}}, 
 {"id":"6fFQV2V8","user_id":"22f7f961-1151-4660-85f4-ad5d9f042958","name":"new level","description":"auto desc","published":true,"data":{"rooms": [{"scale": 2, "stage": {"locked": false, "matrix": ["", "", "", "", "", "", "", "", "", "", "", "", "", "", "", "", "", "", ["", "", "", "", "", "", "", "", "", "", "", "?", "?", "", "", "", "", "", "", "", "", "", "", "", "", "", "?", "?", "?"], ["", "", "", "", "", "", "", "", "", "", "", "", "", "", "", "", "", "", "", "", "", "", "", "", "", "", "", "", "", "", "Flwa", "", "", "", "", "", "", "", "", "", "", "", "", "", "", "", "", "", "", "", "", "", "", "", "", "", "", "", "", "", "", "", "", "", "", "", "?", "", "", "", "", "", "", "", "", "", "", "", "", "", "", "", "?"], ["", "", "", "", "", "", "", "", "", "", "", "Flwa", "", "", "", "", "", "", "", "", "", "", "", "", "", "", "", "Flwa", "Flwa", "", "?", "", "", "", "", "", "", "", "", "", "", "", "", "", "", "", "", "", "", "", "", "", "", "?"], ["", "", "", "", "", "", "", "", "", "", "", "", "", "", "", "?", "", "", "", "", "", "", "", "", "", "", "", "", "", "", "", "", "", "", "", "", "", "", "", "", "", "", "", "", "", "Flwa", "Flwa", "", "", "", "", "", "", "", "", "", "", "", "", "", "", "", "", "", "", "", "", "", "", "", "", "", "", "", "", "", "", "", "", "?"], ["", "", "", "", "", "", "", "", "", "", "", "", "", "", "", "", "", "", "", "", "", "", "", "", "", "", "", "", "", "", "", "", "", "", "", "", "", "", "", "", "", "", "", "", "", "", "", "", "", "", "", "", "", "", "", "", "", "", "", "", "", "", "", "", "", "", "", "", "", "", "", "", "", "", "", "", "", "", "", "", "", "", "", "", "", "", "?", "?", "?"], ["", "", "", "", "", "", "", "", "", "", "", "", "", "", "", "Flwa", "", "", "", "", "", "", "", "", "", "", "", "", "", "", "", "", "", "", "", "", "", "?", "", "", "", "", "", "", "", "", "", "", "", "", "", "", "", "", "", "", "", "", "", "", "", "", "?", "?", "?"], ["", "", "", "", "", "", "", "", "", "", "", "", "", "", "", "", "", "", "", "", "", "", "", "", "", "", "", "", "", "", "", "", "", "Flwa", "", "", "", "", "", "", "", "", "", "", "", "", "", "", "", "", "", "", "", "", "", "", "", "", "", "", "", "", "", "", "", "", "", "", "", "", "", "", "", "", "", "", "", "", "", "", "", "", "", "", "", "", "", "", "", "", "", "", "", ""], ["", "", "", "", "", "", "", "", "Flwa", "", "", "", "", "", "", "", "", "", "", "", "", "", "", "", "", "", "", "", "", "", "", "", "", "", "", "", "Flwa", "Flwa", "", "", "", "", "", "Flwa", "", "", "", "", "", "", "", "", "", "", "", "Flwa", "", "", "", "Flwa", "Flwa", "", "", "", "", "", "", "", "Flwa", "Flwa", "", "", "", "", "", "", "", "", "", "", "", "", "", "", "", "", "", "", "", "", "", "", "", "", "", ""], ["", "", "", "", "", "", "", "", "", "", "", "", "", "", "", "", "", "", "", "", "", "", "", "", "", "", "", "", "", "", "", "", "", "", "", "", "", "", "", "", "", "", "", "", "", "", "", "", "", "", "", "", "", "", "", "", "", "", "", "", "", "", "", "", "", "", "", "", ""]], "entities": [{"x": 32, "y": 384, "id": 257, "type": "ArrowSign", "settings": {"direction": "right"}}, {"x": 160, "y": 336, "id": 258, "type": "ColorfulMetalBox", "settings": {"color": "white", "width": 4, "height": 5}}, {"x": 208, "y": 384, "id": 259, "type": "ColorfulMetalBox", "settings": {"color": "orange", "width": 4, "height": 2}}, {"x": 304, "y": 352, "id": 262, "type": "PipeVertical", "settings": {"height": 4, "resizing": false, "direction": "up"}}, {"x": 384, "y": 336, "id": 266, "type": "ColorfulMetalBox", "settings": {"color": "white", "width": 7, "height": 5}}, {"x": 336, "y": 384, "id": 268, "type": "ColorfulMetalBox", "settings": {"color": "white", "width": 7, "height": 2}}, {"x": 480, "y": 400, "id": 270, "type": "WoodFloor", "settings": {"width": 5, "height": 1}}, {"x": 720, "y": 352, "id": 285, "type": "ColorfulMetalBox", "settings": {"color": "white", "width": 3, "height": 4}}, {"x": 640, "y": 384, "id": 286, "type": "PipeVertical", "settings": {"height": 2, "direction": "up"}}, {"x": 48, "y": 368, "id": 298, "type": "BackgroundHillsStripedSmall"}, {"x": 256, "y": 368, "id": 299, "type": "BackgroundHillsStripedSmall"}, {"x": 336, "y": 336, "id": 300, "type": "BackgroundHillsStripedSmall"}, {"x": 832, "y": 368, "id": 301, "type": "WoodFloor", "settings": {"width": 2, "height": 3}}, {"x": 1040, "y": 352, "id": 304, "type": "PipeVertical", "settings": {"height": 4, "resizing": false, "direction": "up"}}, {"x": 1296, "y": 352, "id": 333, "type": "WoodFloor", "settings": {"width": 2, "height": 4}}, {"x": 1264, "y": 384, "id": 334, "type": "WoodFloor", "settings": {"width": 4, "height": 2}}, {"x": 768, "y": 368, "id": 340, "type": "BackgroundHillsStripedSmall"}, {"x": 992, "y": 368, "id": 341, "type": "BackgroundHillsStripedSmall"}, {"x": 0, "y": 416, "id": 361, "type": "WoodFloor", "settings": {"width": 96, "height": 1}}, {"x": 1136, "y": 0, "id": 362, "type": "EndOfLevelBackdrop"}, {"x": 1456, "y": 368, "id": 382, "type": "PipeVertical", "settings": {"height": 3, "resizing": false, "direction": "up"}}], "matrixSettings": [{"s": {"payload": "FireFlower"}, "x": 27, "y": 18}, {"s": {"payload": "Leaf"}, "x": 30, "y": 20}, {"s": {"payload": "Leaf"}, "x": 15, "y": 21}]}, "actors": {"locked": false, "matrix": [], "entities": [{"x": 48, "y": 400, "id": 1, "type": "Player"}, {"x": 176, "y": 400, "id": 261, "type": "Goomba"}, {"x": 304, "y": 352, "id": 263, "type": "PiranhaPlantRedFire"}, {"x": 368, "y": 368, "id": 269, "type": "Goomba"}, {"x": 512, "y": 384, "id": 280, "type": "RedKoopaTroopa"}, {"x": 416, "y": 400, "id": 282, "type": "Goomba"}, {"x": 672, "y": 400, "id": 283, "type": "Goomba"}, {"x": 608, "y": 400, "id": 284, "type": "Goomba"}, {"x": 640, "y": 384, "id": 287, "type": "PiranhaPlantRedFire"}, {"x": 848, "y": 352, "id": 302, "type": "RedKoopaTroopa"}, {"x": 928, "y": 400, "id": 314, "type": "Goomba"}, {"x": 1392, "y": 288, "id": 332, "type": "CardSlotMachine"}, {"x": 1040, "y": 352, "id": 360, "type": "PiranhaPlantRedFire"}, {"x": 1328, "y": 400, "id": 363, "type": "Goomba"}, {"x": 1392, "y": 400, "id": 364, "type": "Goomba"}, {"x": 1456, "y": 368, "id": 383, "type": "PiranhaPlantRedFire"}, {"x": 1168, "y": 400, "id": 384, "type": "RedKoopaTroopa"}, {"x": 1120, "y": 400, "id": 385, "type": "Goomba"}, {"x": 1248, "y": 400, "id": 386, "type": "Goomba"}, {"x": 1392, "y": 336, "id": 387, "type": "GreenKoopaTroopa"}], "matrixSettings": []}, "settings": {"music": 0, "bgColor": 132, "bgGraphic": 5, "bgExtraColorAndEffect": 0}, "scrollOffset": {"x": 1035.5, "y": 80.75}, "roomTileWidth": 96, "paletteEntries": ["PipeVertical", "QuestionBlock", "WoodFloor", "CardSlotMachine", "EndOfLevelBackdrop", "BackgroundHillsStripedSmall", "FlowerBushAlternate", "PiranhaPlantRedFire", "Mushroom", "RedKoopaTroopa", "GreenKoopaTroopa", "Goomba", "ColorfulMetalBox", "ArrowSign", "Brick", "Coin", "WoodBlock", "PSwitch"], "roomTileHeight": 27, "canDecreaseScale": true, "canIncreaseScale": true, "currentPaletteEntry": "GreenKoopaTroopa"}], "settings": {"timer": 900}},"parent_id":"6fFQV2V8","save_version":1,"created_at":"2023-09-10T16:16:34.927854","updated_at":"2023-09-10T16:16:34.927854","version":"5.2.0","user":{"username":"camilo"}}]