[{"id":"-9Qw0gl5","user_id":"76eac040-94de-49f8-be9c-9f60dafb1a69","name":"just a test for fun","description":"auto desc","published":true,"data":{"rooms": [{"scale": 3.75, "stage": {"locked": false, "matrix": ["", "", "", "", "", "", "", "", "", "", "", "", "", "", "", "", "", ["", "", "", "", "", "", "", "", "", "", "", "", "", "", "", "", "", "Wo"], "", "", "", "", "", ["", "", "", "", "", "", "", "", "", "", "", "", "", "", "", "", "", "", "", "", "", "BuMM"], ["Wo", "Wo", "Wo", "Wo", "Wo", "Wo", "Wo", "Wo", "Wo", "Wo", "Wo", "Wo", "Wo", "Wo", "Wo", "Wo", "Wo", "Wo", "Wo", "Wo", "Wo", "Wo", "Wo", "Wo", "Wo", "Wo", "Wo", "Wo", "Wo", "Wo", "Wo", "Wo", "Wo", "Wo", "Wo", "Wo", "Wo", "Wo", "Wo", "Wo", "Wo", "Wo", "Wo", "Wo", "Wo", "Wo", "Wo", "Wo", "Wo", "Wo", "Wo", "Wo", "Wo", "Wo", "Wo", "Wo", "Wo", "Wo", "Wo", "Wo", "Wo", "Wo", "Wo", "Wo", "Wo", "Wo", "Wo", "Wo", "Wo", "Wo", "Wo", "Wo", "Wo", "Wo", "Wo", "Wo", "Wo", "Wo", "Wo", "Wo", "Wo", "Wo", "Wo", "Wo", "Wo", "Wo", "Wo", "Wo", "Wo", "Wo", "Wo", "Wo", "Wo", "Wo", "Wo", "Wo"], ["", "", "", "", "", "", "", "", "", "", "", "", "", "", "", "", "", "", "", "", "", "", "", "", "", "", "", "", "", "", "", "", "", "", "", "", "", "", "", "", "", "", "", "", "", "", "", "", "Wo", "", "", "", "", "", "", "", "", "", "", "", "", "", "", "", "", "Wo", "Wo", "Wo", "Wo", "Wo", "Wo", "Wo", "Wo", "Wo", "Wo", "Wo", "Wo", "Wo", "Wo", "Wo", "Wo", "Wo", "Wo", "Wo", "Wo", "Wo", "Wo", "Wo", "Wo", "Wo", "Wo", "Wo", "Wo", "Wo", "Wo", "Wo"], ""], "entities": [{"x": 176, "y": 336, "id": 189, "type": "ECoin", "settings": {"coinData": [0, 0, 0, 0, 0, 0, 0, 17, 0, 0, 17, 33, 0, 16, 33, 211, 0, 17, 210, 221, 0, 33, 221, 221, 16, 33, 221, 221, 16, 50, 221, 221, 17, 17, 17, 17, 33, 50, 51, 28, 50, 221, 221, 205, 221, 221, 221, 221, 221, 221, 221, 221, 221, 157, 17, 153, 221, 153, 153, 153, 157, 24, 153, 153, 0, 0, 0, 0, 17, 0, 0, 0, 27, 17, 0, 0, 189, 27, 1, 0, 221, 221, 17, 0, 17, 209, 27, 0, 153, 17, 27, 1, 153, 25, 188, 1, 17, 210, 221, 221, 33, 211, 221, 221, 33, 221, 221, 221, 193, 221, 221, 141, 193, 25, 17, 145, 177, 153, 25, 17, 177, 156, 153, 25, 17, 139, 153, 25, 157, 221, 157, 153, 24, 221, 157, 153, 218, 29, 153, 25, 154, 137, 136, 217, 136, 136, 136, 25, 17, 145, 136, 153, 17, 17, 137, 153, 17, 17, 145, 153, 153, 25, 177, 17, 17, 25, 193, 26, 221, 17, 17, 26, 221, 29, 17, 26, 221, 221, 17, 26, 221, 29, 17, 26, 209, 29, 17, 26, 25, 17, 97, 17, 16, 203, 153, 25, 16, 177, 17, 17, 0, 177, 221, 221, 0, 17, 219, 221, 0, 16, 177, 203, 0, 0, 17, 161, 0, 0, 0, 17, 0, 0, 0, 0, 17, 17, 136, 153, 17, 145, 152, 153, 157, 153, 153, 153, 29, 29, 153, 17, 221, 221, 29, 17, 106, 221, 221, 166, 161, 170, 170, 26, 17, 17, 17, 17, 153, 17, 161, 1, 25, 17, 22, 1, 17, 97, 26, 0, 17, 166, 17, 0, 166, 26, 1, 0, 26, 17, 0, 0, 17, 0, 0, 0, 0, 0, 0, 0]}}], "matrixSettings": []}, "actors": {"locked": false, "matrix": [], "entities": [{"x": 32, "y": 368, "id": 1, "type": "Player"}, {"x": 368, "y": 320, "id": 188, "type": "CardSlotMachine"}, {"x": 272, "y": 288, "id": 192, "type": "Swooper"}, {"x": 416, "y": 384, "id": 194, "type": "MontyMole"}, {"x": 96, "y": 368, "id": 195, "type": "CapeFeather"}], "matrixSettings": []}, "settings": {"music": 170, "bgColor": 132, "bgGraphic": 8, "bgExtraColorAndEffect": 0}, "scrollOffset": {"x": 27.466666666666246, "y": 263.7333333333334}, "roomTileWidth": 96, "paletteEntries": ["CapeFeather", "MontyMole", "Swooper", "BuriedVegetableMontyMole", "ECoin", "Brick", "Coin", "WoodBlock", "Goomba", "QuestionBlock", "GreenKoopaTroopa", "PipeVertical", "CardSlotMachine", "PSwitch"], "roomTileHeight": 27, "canDecreaseScale": true, "canIncreaseScale": true, "currentPaletteEntry": "CapeFeather"}], "settings": {"timer": 900, "description": "just something i (im not good at making levels or like doing these type of stuff so please forgive me)"}},"parent_id":"-9Qw0gl5","save_version":1,"created_at":"2022-11-25T00:57:27.406271","updated_at":"2022-11-25T01:03:36.792903","version":"5.2.0","user":{"username":"ianthekoopa"}}]